Baron_iq/__init__.py
Baron_iq/baron_class.py
Baron_iq/baron_class2.py
Baroniq-0.0.2.dist-info/LICENSE
Baroniq-0.0.2.dist-info/METADATA
Baroniq-0.0.2.dist-info/WHEEL
Baroniq-0.0.2.dist-info/top_level.txt
Baroniq-0.0.2.dist-info/RECORD
