Metadata-Version: 2.1
Name: Baroniq
Version: 0.0.2
Summary: my God
Home-page: https://github.com/baronblack7/Baroniq
Author: Falh Gomer
Author-email: aowrass45467@gmail.com
License: UNKNOWN
Project-URL: Bug Tracker, https://github.com/pypa/sampleproject/issues
Platform: UNKNOWN
Classifier: Programming Language :: Python :: 3
Classifier: License :: OSI Approved :: MIT License
Classifier: Operating System :: OS Independent
Requires-Python: >=3.6
License-File: LICENSE
Requires-Dist: requests
